LICENSE
MANIFEST.in
README.rst
requirements.txt
setup.py
trequests/__init__.py
trequests/trequests_version.txt
trequests.egg-info/PKG-INFO
trequests.egg-info/SOURCES.txt
trequests.egg-info/dependency_links.txt
trequests.egg-info/requires.txt
trequests.egg-info/top_level.txt