Metadata-Version: 1.0
Name: trequests
Version: 0.9.5
Summary: A Tornado async HTTP/HTTPS client adaptor for python-requests
Home-page: https://github.com/1stvamp/trequests
Author: Wes Mason
Author-email: wes@1stvamp.org
License: BSD
Platform: UNKNOWN
